cart_chunk/__init__.py
cart_chunk/cart_chunk.py
cart_chunk/defines.py
python_cart_chunk-0.0.2b2.dist-info/LICENSE
python_cart_chunk-0.0.2b2.dist-info/METADATA
python_cart_chunk-0.0.2b2.dist-info/WHEEL
python_cart_chunk-0.0.2b2.dist-info/top_level.txt
python_cart_chunk-0.0.2b2.dist-info/RECORD
