Metadata-Version: 2.1
Name: python_cart_chunk
Version: 0.0.2b2
Summary: Add CART CHUNK to wave files.
Author-email: Tim Finley <tim.finley24@gmail.com>
Maintainer-email: Tim Finley <tim.finley24@gmail.com>
License: MIT License
Requires-Python: >=3.10
License-File: LICENSE
